sandcage.py
sandcage-0.2.0.dist-info/DESCRIPTION.rst
sandcage-0.2.0.dist-info/METADATA
sandcage-0.2.0.dist-info/RECORD
sandcage-0.2.0.dist-info/WHEEL
sandcage-0.2.0.dist-info/metadata.json
sandcage-0.2.0.dist-info/top_level.txt
