Metadata-Version: 2.0
Name: sandcage
Version: 0.2.0
Summary: Python client library for SandCage's API
Home-page: https://github.com/sandcage/sandcage-api-python
Author: Antti Nykanen <ajjn@iki.fi>, Evangelos Kokkonos
Author-email: ajjn@iki.fi
License: Apache License Version 2.0
Keywords: api http development
Platform: UNKNOWN
Classifier: Development Status :: 4 - Beta
Classifier: Intended Audience :: Developers
Classifier: Topic :: Internet :: WWW/HTTP :: Dynamic Content
Classifier: License :: OSI Approved :: Apache Software License
Classifier: Programming Language :: Python :: 2
Classifier: Programming Language :: Python :: 2.7
Classifier: Programming Language :: Python :: 3
Classifier: Programming Language :: Python :: 3.2
Classifier: Programming Language :: Python :: 3.3
Classifier: Programming Language :: Python :: 3.4
Classifier: Programming Language :: Python :: 3.5
Requires-Dist: certifi
Requires-Dist: requests
